myst_spec/__init__.py
myst_spec/version.py
myst_spec-0.0.1.dist-info/LICENSE
myst_spec-0.0.1.dist-info/METADATA
myst_spec-0.0.1.dist-info/WHEEL
myst_spec-0.0.1.dist-info/top_level.txt
myst_spec-0.0.1.dist-info/RECORD
